api_mlops_project/__init__.py
api_mlops_project/data_loader.py
api_mlops_project/dataframe_checker.py
api_mlops_project/feature_engineering_predict.py
api_mlops_project/main.py
api_mlops_project/pipeline_utils.py
api_mlops_project/shape.py
api_mlops_project-0.1.0.dist-info/entry_points.txt
api_mlops_project-0.1.0.dist-info/LICENSE
api_mlops_project-0.1.0.dist-info/METADATA
api_mlops_project-0.1.0.dist-info/WHEEL
api_mlops_project-0.1.0.dist-info/RECORD
