Metadata-Version: 2.1
Name: api-mlops-project
Version: 0.1.0
Summary: This project aims to apply MLOps techniques to deploy a machine learning model through an API constructed with FastAPI.
License: MIT
Author: Junior Torres
Author-email: galas.apps@gmail.com
Requires-Python: >=3.8.10,<4.0.0
Classifier: Development Status :: 4 - Beta
Classifier: License :: OSI Approved :: MIT License
Classifier: Natural Language :: English
Classifier: Programming Language :: Python :: 3
Classifier: Programming Language :: Python :: 3.9
Classifier: Programming Language :: Python :: 3.10
Classifier: Programming Language :: Python :: 3.11
Classifier: Programming Language :: Python :: 3.8
Classifier: Topic :: Scientific/Engineering :: Artificial Intelligence
Classifier: Topic :: Software Development :: Libraries :: Python Modules
Requires-Dist: fastapi[all] (>=0.100.1,<0.101.0)
Requires-Dist: pyarrow (>=12.0.1,<13.0.0)
Requires-Dist: pydantic (>=2.1.1,<3.0.0)
Requires-Dist: python-multipart (>=0.0.6,<0.0.7)
Requires-Dist: scikit-learn (==1.0.2)
Requires-Dist: uvicorn (>=0.23.2,<0.24.0)
Project-URL: Code, https://github.com/JuniorTorresMTJ/model_api_mlops_project
Project-URL: Documentation, https://mlops-shape-project.readthedocs.io/en/latest/
